odoo/addons/product_company_default/README.rst
odoo/addons/product_company_default/__init__.py
odoo/addons/product_company_default/__manifest__.py
odoo/addons/product_company_default/data/ir_config_parameter.xml
odoo/addons/product_company_default/demo/demo_ir_config_parameter.xml
odoo/addons/product_company_default/i18n/it.po
odoo/addons/product_company_default/i18n/product_company_default.pot
odoo/addons/product_company_default/models/__init__.py
odoo/addons/product_company_default/models/product_template.py
odoo/addons/product_company_default/readme/DESCRIPTION.md
odoo/addons/product_company_default/static/description/icon.png
odoo/addons/product_company_default/static/description/index.html
odoo/addons/product_company_default/tests/__init__.py
odoo/addons/product_company_default/tests/test_product_company_default.py
odoo_addon_product_company_default-18.0.1.0.0.2.dist-info/METADATA
odoo_addon_product_company_default-18.0.1.0.0.2.dist-info/WHEEL
odoo_addon_product_company_default-18.0.1.0.0.2.dist-info/top_level.txt
odoo_addon_product_company_default-18.0.1.0.0.2.dist-info/RECORD
